odoo/addons/purchase_order_secondary_unit/README.rst
odoo/addons/purchase_order_secondary_unit/__init__.py
odoo/addons/purchase_order_secondary_unit/__manifest__.py
odoo/addons/purchase_order_secondary_unit/i18n/es.po
odoo/addons/purchase_order_secondary_unit/i18n/fr.po
odoo/addons/purchase_order_secondary_unit/i18n/ja.po
odoo/addons/purchase_order_secondary_unit/i18n/purchase_order_secondary_unit.pot
odoo/addons/purchase_order_secondary_unit/models/__init__.py
odoo/addons/purchase_order_secondary_unit/models/product_template.py
odoo/addons/purchase_order_secondary_unit/models/purchase_order.py
odoo/addons/purchase_order_secondary_unit/readme/CONTRIBUTORS.rst
odoo/addons/purchase_order_secondary_unit/readme/DESCRIPTION.rst
odoo/addons/purchase_order_secondary_unit/readme/USAGE.rst
odoo/addons/purchase_order_secondary_unit/static/description/icon.png
odoo/addons/purchase_order_secondary_unit/static/description/index.html
odoo/addons/purchase_order_secondary_unit/tests/__init__.py
odoo/addons/purchase_order_secondary_unit/tests/test_purchase_order_secondary_unit.py
odoo/addons/purchase_order_secondary_unit/views/product_views.xml
odoo/addons/purchase_order_secondary_unit/views/purchase_order_views.xml
odoo14_addon_purchase_order_secondary_unit-14.0.2.0.1.dist-info/METADATA
odoo14_addon_purchase_order_secondary_unit-14.0.2.0.1.dist-info/WHEEL
odoo14_addon_purchase_order_secondary_unit-14.0.2.0.1.dist-info/top_level.txt
odoo14_addon_purchase_order_secondary_unit-14.0.2.0.1.dist-info/RECORD
