Metadata-Version: 2.1
Name: odoo14-addon-purchase-order-secondary-unit
Version: 14.0.2.0.1
Summary: Purchase product in a secondary unit
Home-page: https://github.com/OCA/purchase-workflow
Author: Tecnativa, Odoo Community Association (OCA)
Author-email: support@odoo-community.org
License: AGPL-3
Platform: UNKNOWN
Classifier: Programming Language :: Python
Classifier: Framework :: Odoo
Classifier: Framework :: Odoo :: 14.0
Classifier: License :: OSI Approved :: GNU Affero General Public License v3
Classifier: Development Status :: 4 - Beta
Requires-Python: >=3.6
Requires-Dist: odoo14-addon-product-secondary-unit
Requires-Dist: odoo (<14.1dev,>=14.0a)
